{
  "ticker": "GH",
  "name": "Guardant Health",
  "header": {
    "name": "Guardant Health",
    "ticker": "GH",
    "sector": "Healthcare AI",
    "sector_id": "healthcare_ai",
    "market": "US",
    "tier": 3,
    "ai_role": "液体活检 + AI 肿瘤早筛",
    "price": 98.66000366210938,
    "change_1d": 0.19,
    "composite": 68.94871794871794,
    "tier_letter": "C",
    "description": [
      "Guardant Health 的 AI 产业链位置为 Healthcare AI。",
      "AI 角色：液体活检 + AI 肿瘤早筛。当前内部综合评分 68。",
      "Healthcare AI 板块在 AI 数据中心 capex 周期中处于关键位置。"
    ],
    "data_warning": null,
    "data_source_text": "Yahoo Finance · 更新 2026-05-15 05:16:08",
    "status_label": "持有"
  },
  "panels": [
    {
      "id": "technical",
      "title": "价格与技术指标",
      "type": "metrics_grid",
      "data": {
        "最新价": "$98.66",
        "日内涨跌": "+0.19%",
        "1日涨跌": "+0.19%",
        "5日涨跌": "+3.09%",
        "1月涨跌": "+14.19%",
        "3月涨跌": "-5.90%",
        "6月涨跌": "+4.55%",
        "1年涨跌": "+142.29%",
        "YTD涨跌": "-3.03%",
        "20日均线": "91.12",
        "50日均线": "89.10",
        "200日均线": "85.80",
        "RSI 14": "62.95",
        "MACD": "2.45",
        "20日波动率": "43.17%",
        "成交量": "1,151,935",
        "量比20日": "0.58",
        "52周高点": "120.74",
        "52周低点": "36.36",
        "距52周高点": "-18.29%",
        "距52周低点": "+171.34%",
        "20日支撑": "79.01",
        "20日压力": "100.73"
      }
    },
    {
      "id": "fundamentals",
      "title": "基本面与产业链",
      "type": "mixed",
      "data": {
        "AI产业链位置": "Healthcare AI",
        "AI角色": "液体活检 + AI 肿瘤早筛",
        "投资确定性": "—",
        "收入": "$1.08B",
        "收入同比": "48.30%",
        "毛利率": "64.90%",
        "经营利润率": "-40.23%",
        "净利率": "-40.10%",
        "经营现金流": "—",
        "资本开支": "-$49.43M",
        "自由现金流": "-$85.45M",
        "FCF 利润率": "-7.91%",
        "现金及短投": "$1.10B",
        "总债务": "$1.70B",
        "净现金/债务": "-$400.71M",
        "流通股本": "132.60M",
        "ROE": "—",
        "债务/权益": "0.13",
        "市值": "$13.08B",
        "企业价值": "$13.66B",
        "市盈率 TTM": "—",
        "预期市盈率": "-155.63",
        "市销率": "12.11",
        "EV / 营收": "12.64",
        "EV / EBITDA": "-33.47",
        "EV / FCF": "-159.85",
        "FCF 收益率": "-0.65%",
        "估值分位": "—",
        "内部合理区间": "—"
      }
    },
    {
      "id": "scores",
      "title": "评分",
      "type": "score_grid_3x3",
      "data": [
        {
          "label": "业务质量",
          "value": null,
          "reasoning": null,
          "is_ai": false,
          "is_quant": true,
          "formula": "0.30 * ROE 分位 +\n0.30 * 毛利率 分位 +\n0.20 * 净利率 分位 +\n0.20 * 营业利润率 分位"
        },
        {
          "label": "护城河",
          "value": 72.0,
          "reasoning": "Guardant拥有Reveal/Shield等FDA获批液体活检产品及大量专利，先发优势显著；临床数据积累形成Know-how壁垒；医院/保险覆盖网络构成切换成本。但竞争者（Foundation Medicine、Grail）持续追赶，净利率-40%显示商业化仍在爬坡，护城河尚在固化中。",
          "is_ai": true,
          "is_quant": false
        },
        {
          "label": "AI 暴露度",
          "value": 32.0,
          "reasoning": "GH核心价值在液体活检技术（cfDNA测序）和临床验证，AI是分析管线的组成部分而非独立产品。收入驱动来自Shield/Reveal等检测产品的商业化，AI能力提升检测精度但不直接对应AI capex支出。AI退潮不影响核心业务逻辑。",
          "is_ai": true,
          "is_quant": false
        },
        {
          "label": "成长性",
          "value": 83.33333333333334,
          "reasoning": null,
          "is_ai": false,
          "is_quant": true,
          "formula": "0.60 * 营收同比 分位 +\n0.40 * YTD 涨幅 分位"
        },
        {
          "label": "盈利能力",
          "value": null,
          "reasoning": null,
          "is_ai": false,
          "is_quant": true,
          "formula": "0.40 * 营业利润率 分位 +\n0.30 * 净利率 分位 +\n0.30 * ROE 分位"
        },
        {
          "label": "估值",
          "value": 73.33333333333334,
          "reasoning": null,
          "is_ai": false,
          "is_quant": true,
          "formula": "100 - (0.40 * 预期 PE 分位 +\n       0.30 * EV/EBITDA 分位 +\n       0.30 * EV/营收 分位)"
        },
        {
          "label": "动量",
          "value": 88.33333333333333,
          "reasoning": null,
          "is_ai": false,
          "is_quant": true,
          "formula": "0.30 * 1 月涨幅 分位 +\n0.25 * 3 月涨幅 分位 +\n0.20 * 6 月涨幅 分位 +\n0.15 * RSI(14) 分位 +\n0.10 * 距 52 周高 分位"
        },
        {
          "label": "风险",
          "value": 28.0,
          "reasoning": "GH持续亏损，长期负债15亿超现金11亿，偿债压力大；液体活检赛道竞争激烈（Illumina/Grail等），商业化进展慢；医保覆盖政策不确定性高；估值依赖未来增长预期，回撤风险显著。综合财务与业务风险偏高。",
          "is_ai": true,
          "is_quant": false
        },
        {
          "label": "综合 · Warren",
          "value": 68.94871794871794,
          "is_composite": true,
          "formula": "综合分 = 0.25×业务质量 + 0.20×护城河 + 0.20×估值 + 0.10×成长性 + 0.10×盈利能力 + 0.05×AI 暴露度 + 0.05×风险 + 0.05×动量"
        }
      ]
    },
    {
      "id": "external_views",
      "title": "外部观点",
      "type": "external",
      "title_meta": "Yahoo Finance · 20 位分析师 · 2026-05-15 05:16:08",
      "data": {
        "target_mean": 130.55,
        "target_high": 190.0,
        "target_low": 90.0,
        "upside_pct": 32.32,
        "rating": "strong_buy",
        "rating_letter": "A",
        "rating_change": "维持",
        "previous_rating_letter": "A",
        "n_analysts": 20,
        "next_earnings": "2026-07-30",
        "eps_estimate": -0.39466,
        "revenue_estimate": null
      },
      "disclaimer": "仅作外部市场预期参考，不覆盖 AI 投资观点的内部买卖价。"
    },
    {
      "id": "ai_view",
      "title": "Guardant Health（GH）AI 投资观点",
      "type": "ai_text",
      "data": {
        "text": "【moat】Guardant拥有Reveal/Shield等FDA获批液体活检产品及大量专利，先发优势显著；临床数据积累形成Know-how壁垒；医院/保险覆盖网络构成切换成本。但竞争者（Foundation Medicine、Grail）持续追赶，净利率-40%显示商业化仍在爬坡，护城河尚在固化中。 【ai_exposure】GH核心价值在液体活检技术（cfDNA测序）和临床验证，AI是分析管线的组成部分而非独立产品。收入驱动来自Shield/Reveal等检测产品的商业化，AI能力提升检测精度但不直接对应AI capex支出。AI退潮不影响核心业务逻辑。 【risk】GH持续亏损，长期负债15亿超现金11亿，偿债压力大；液体活检赛道竞争激烈（Illumina/Grail等），商业化进展慢；医保覆盖政策不确定性高；估值依赖未来增长预期，回撤风险显著。综合财务与业务风险偏高。"
      }
    },
    {
      "id": "news",
      "title": "相关新闻 (近 7 天)",
      "type": "news_list",
      "data": [
        {
          "date": "2026-05-15",
          "source": "seekingalpha.com",
          "url": "https://seekingalpha.com/symbol/GH/news?page=4",
          "title": "Guardant Health, Inc. (GH) Latest Stock News | Seeking Alpha",
          "sentiment": null,
          "impact": null
        },
        {
          "date": "2026-05-15",
          "source": "marketwatch.com",
          "url": "https://www.marketwatch.com/investing/stock/gh",
          "title": "GH Stock Price | Guardant Health Inc. Stock Quote (U.S.: Nasdaq) | MarketWatch",
          "sentiment": null,
          "impact": null
        },
        {
          "date": "2026-05-15",
          "source": "cnbc.com",
          "url": "https://www.cnbc.com/quotes/GH",
          "title": "GH: Guardant Health Inc - Stock Price, Quote and News - CNBC",
          "sentiment": null,
          "impact": null
        },
        {
          "date": "2026-05-15",
          "source": "finance.yahoo.com",
          "url": "https://finance.yahoo.com/news/guardant-health-gh-valuation-focus-021321780.html",
          "title": "Guardant Health (GH): Valuation in Focus After Obamacare Subsidy ...",
          "sentiment": null,
          "impact": null
        },
        {
          "date": "2026-05-15",
          "source": "finance.yahoo.com",
          "url": "https://finance.yahoo.com/quote/GH/news/",
          "title": "Guardant Health, Inc. (GH) Latest Stock News & Headlines",
          "sentiment": null,
          "impact": null
        },
        {
          "date": "2026-05-15",
          "source": "finance.yahoo.com",
          "url": "https://finance.yahoo.com/quote/GH.MX/news/",
          "title": "Guardant Health, Inc. (GH.MX) Latest Stock News & Headlines ...",
          "sentiment": null,
          "impact": null
        },
        {
          "date": "2026-05-15",
          "source": "seekingalpha.com",
          "url": "https://seekingalpha.com/symbol/GH",
          "title": "Guardant Health, Inc. (GH) Stock Price, Quote, News & Analysis",
          "sentiment": null,
          "impact": null
        },
        {
          "date": "2026-05-15",
          "source": "finance.yahoo.com",
          "url": "https://finance.yahoo.com/news/wall-street-positive-opinion-guardant-124009109.html",
          "title": "Wall Street Has a Positive Opinion on Guardant Health (GH)",
          "sentiment": null,
          "impact": null
        },
        {
          "date": "2026-05-13",
          "source": "StockStory",
          "url": "https://finance.yahoo.com/news/gh-q1-deep-dive-shield-114055837.html",
          "title": "GH Q1 Deep Dive: Shield Volume Acceleration and Oncology Portfolio Expansion Fuel Growth",
          "sentiment": null,
          "impact": null
        },
        {
          "date": "2026-05-12",
          "source": "Insider Monkey",
          "url": "https://finance.yahoo.com/sectors/healthcare/articles/evercore-isi-keeps-line-rating-000206412.html",
          "title": "Evercore ISI Keeps an “In Line” Rating on Guardant Health, Inc. (GH)",
          "sentiment": null,
          "impact": null
        }
      ]
    },
    {
      "id": "score_history",
      "title": "评分历史曲线 (12 周)",
      "type": "chart",
      "data": [
        {
          "date": "2026-05-13",
          "value": 67.9230769230769
        },
        {
          "date": "2026-05-15",
          "value": 68.94871794871794
        }
      ]
    }
  ],
  "updated_at": "2026-05-15"
}